Carter-Offline/__init__.py
Carter-Offline/chat.py
Carter-Offline/main.py
Carter-Offline/Carter-Offline-SubFolder/JanexSub.py
Carter-Offline/Carter-Offline-SubFolder/__init__.py
CarterOffline/__init__.py
CarterOffline/chat.py
CarterOffline/main.py
CarterOffline/Carter-Offline-SubFolder/JanexSub.py
CarterOffline/Carter-Offline-SubFolder/__init__.py
Carter_Offline-2.0.6.dist-info/LICENSE
Carter_Offline-2.0.6.dist-info/METADATA
Carter_Offline-2.0.6.dist-info/WHEEL
Carter_Offline-2.0.6.dist-info/top_level.txt
Carter_Offline-2.0.6.dist-info/RECORD
